{
  "job_id": "varsha-hm-merchandiser",
  "person_id": "varsha",
  "job_title": "Senior Merchandiser -- Women's Wear (Jersey)",
  "company": "H&M",
  "job_url": "https://www.linkedin.com/jobs/view/hm-senior-merchandiser-womens-wear",
  "jd_text": "Job Title: Senior Merchandiser -- Women's Wear (Jersey)\nCompany: H&M Group\nLocation: Bengaluru, India\nEmployment Type: Full-Time\nExperience Level: 4-6 years\n\nABOUT THE ROLE\nAs a Senior Merchandiser in our Women's Wear Jersey team, you will drive range planning and\nassortment strategy for one of our key product categories. You will work closely with the buying team,\ndesigners, and regional teams to ensure the right product is in the right place at the right time -- at\nthe right price.\n\nKEY RESPONSIBILITIES\n- Own the OTB (Open-to-Buy) planning and management for the women's jersey category, ensuring\n  optimal stock levels across channels and geographies\n- Lead assortment planning for seasonal and replenishment ranges, balancing trend, commercial\n  viability, and brand positioning\n- Analyze weekly sales performance, sell-through rates, and margin data to make data-driven\n  decisions on replenishment, markdowns, and range adjustments\n- Collaborate with the buying team on range development, identifying trends and translating them\n  into commercial assortment plans\n- Manage supplier/vendor relationships, coordinating on production timelines, MOQs, and delivery\n  schedules to ensure 95%+ on-time delivery\n- Partner with regional teams (India, SEA) to understand local market needs and adapt assortment\n  accordingly\n- Drive category P&L performance by managing margins, stock turn, and sell-through KPIs\n- Lead product lifecycle management (PLM) from range development through end-of-season clearance\n- Conduct range reviews with cross-functional teams including design, marketing, and VM\n\nWHAT WE'RE LOOKING FOR\n- 4-6 years of experience in fashion buying, merchandising, or category management\n- Demonstrated experience with OTB management and assortment planning\n- Strong analytical skills -- Advanced Excel (pivot tables, VLOOKUP, data dashboards), experience\n  with Metabase, Power BI, or similar BI tools is a plus\n- Experience managing PO/PI coordination with multiple vendors and factories\n- Understanding of womenswear trends, especially in the jersey/casualwear category\n- Proven ability to manage multiple suppliers and factories across India and Asia\n- Experience in both offline retail and e-commerce/omnichannel merchandising\n- Familiarity with SAP or other ERP systems (PO/inventory tracking)\n- Strong cross-functional collaboration skills -- you will work closely with buying, design, VM,\n  marketing, and supply chain teams\n- Excellent negotiation skills with track record of improving vendor pricing and MOQs\n\nPREFERRED QUALIFICATIONS\n- NIFT, Pearl Academy, or equivalent fashion institute qualification\n- Experience with fast-fashion or value retail (knowledge of DMart, Zara, Zudio, Mango assortment\n  strategies is a plus)\n- Exposure to category launch or new market entry projects\n- Experience building and operating WIP trackers and production calendars",
  "master_cv": "VARSHA SATHYANARAYANAN\nthisisvarshasathya@gmail.com | +91 8939432182 | www.linkedin.com/in/varshasathya/\nSUMMARY\nFashion professional with 3+ years of experience in buying, merchandising, category management, and P&L management\nacross retail and e-commerce. Experienced in assortment planning, vendor sourcing, PO/PI coordination, and product\nlifecycle execution for apparel categories including bottom-wear, casualwear, and accessories. Proven ability to analyze\nsales performance, optimize assortments, negotiate supplier terms, and improve margins and sell-through across multi-\nchannel retail environments.\nPROFESSIONAL EXPERIENCE\nSuperK Bangalore, India\nCategory Manager – Fashion Nov 2025 – Present\nBuilt the fashion category from near zero across online channels and a tech-enabled retail network of 3+ coco stores,\nlaunching assortments across apparel, footwear, and accessories while driving vendor expansion, category P&L\nmanagement, and data-led merchandising decisions.\n• Expanded the fashion assortment from 5 to 25+ subcategories across menswear, womenswear, kidswear,\nfootwear, and accessories by onboarding 12+ regional vendors, identifying assortment gaps, and benchmarking\ncategory offerings against value retail players like DMart and Vishal Mega Mart.\n• Analyzed weekly sales performance, pricing benchmarks, and customer demand signals thereby generating ₹ 3.5\nlakh in category revenue within two months.\n• Negotiated vendor pricing, MOQs, and sourcing terms, improving product margins from 22% to 35% while\nmaintaining competitive retail pricing.\n• Partnered with marketing teams to launch fashion-led campaigns during New Year, Pongal and Republic Day\nincreasing category visibility by ~22% and driving ~15% uplift in campaign period sales.\n• Collaborated with operations and supply chain teams to improve stock availability for fast-moving SKUs,\ncoordinating warehouse invoicing and inventory flow to reduce stock-outs by ~20% across priority products.\n• Utilized Excel and Metabase dashboards for tracking sell-through, AOV, and margin performance; identified\nunderperforming SKUs and implemented assortment rationalization that improved category gross margin by ~6%.\nThe Style Gram Founder Remote - Chennai, India\nNov 2024 – Jun 2025\nBuilt and operated a lean fashion reselling brand focused on affordable women’s western-wear, managing end-to-end\nsourcing, merchandising, content creation, and customer engagement across Instagram and Swiggy Minis.\n• Generated ₹50,000 in revenue during the launch phase with an average order value of ₹600, fulfilling 80+\ncustomer orders across Tier 1 and Tier 2 cities with zero product returns.\n• Sourced and merchandised 60+ SKUs across tops, skirts, and dresses through direct supplier negotiations,\nmaintaining 45% gross margins and reducing sourcing turnaround time by 25%.\n• Evaluated and engaged 5 supplier partners before finalizing a primary vendor to optimize pricing, quality\nconsistency, and procurement turnaround time.\n• Executed pricing, merchandising, and inventory tracking through Excel-based systems, ensuring 100% order\nfulfillment and streamlined stock management.\n• Managed 60+ SKUs on Swiggy Minis and built a custom Excel-based WIP tracker to manage catalog listings,\norder tracking, and inventory visibility, reducing catalog errors by 90% and improving stock flow for fast-selling\nstyles.\n• Produced 25+ branded content assets and launched 3+ Instagram ad campaigns, improving click-through rates\nby 22% through A/B testing and targeted messaging.\nGo Colors (Go Fashion India Ltd.) Assistant Fashion Manager Chennai, India\nSept 2020 – June 2023\nSupported buying and merchandising for women’s and girls’ bottom-wear categories including leggings, track pants, formal\npants, ethnic bottoms, and shorts, with responsibility for vendor coordination, product lifecycle execution, and data-led\nassortment decisions.\n• Managed PO/PI coordination and vendor communication across 20+ suppliers and 10+ factories across\nIndia and Asia, ensuring 95% on-time delivery for seasonal production orders.\n• Analyzed weekly sales performance for 200+ SKUs, recommending replenishment and assortment adjustments\nthat improved category sell-through by 15%.\n• Aligned assortment planning with trend insights and performance data, driving a 10% lift in customer purchase\nrate across key bottom-wear categories.\n• Launched 3+ new sub-categories including kids-wear, leading a 2-member team to introduce new styles and\nrevamp existing collections, boosting category sales by 15% in the first quarter.\n• Negotiated supplier pricing and MOQs during fabric sourcing and production planning, maintaining product\nquality while ensuring competitive margins.\n• Led sampling, fit approvals, and production coordination for 30+ styles per season, reducing post-launch return\nrates to under 10% while gaining exposure to PLM-driven product development workflows.\n• Built WIP trackers to monitor production timelines and collaborated with logistics, VM, and marketing teams to\nensure timely product launches.\nEDUCATION\nHumber College - Longo School of Business Graduate Certificate in Fashion Management National Institute of Fashion Technology (NIFT) Bachelor of Design - Fashion Design Toronto, Canada\nSept 2023 – Aug 2024\nChennai, India\nJuly 2016 – July 2020\nSKILLS\nCore Competencies: Assortment Planning • Fashion Buying • PO/PI Coordination • Vendor Management • Inventory\nControl • Forecasting • TNA Calendar Tracking • Product Lifecycle Management (PLM) • Order Tracking\nTools: Advanced MS Excel (VLOOKUP, Pivot Tables, Dashboards) • MS Word • Google Sheets • Canva • Meta Ads\nManager • SAP (PO/Inventory Tracking – Basic)\nFunctional Strengths: Cross-Functional Collaboration • Trend Analysis • Sales Performance Reporting • Catalog & Content\nManagement • E-commerce Marketing • Vendor Negotiation",
  "profile": {
    "adjacent_roles": [
      "category manager fashion",
      "fashion product manager",
      "assortment planner",
      "retail buying manager"
    ],
    "assignment_burden_tolerance": 5,
    "benefits_must_have": [
      "health insurance"
    ],
    "confirmed_skills": [
      "fashion buying",
      "fashion merchandising",
      "assortment planning",
      "vendor management",
      "PO/PI coordination",
      "product lifecycle management",
      "category management",
      "inventory management",
      "sourcing",
      "negotiation",
      "excel",
      "data analysis",
      "trend analysis",
      "sell-through analysis",
      "retail operations",
      "e-commerce merchandising",
      "SAP"
    ],
    "ctc_currency": "INR",
    "current_ctc_lakhs": null,
    "equity_required": false,
    "esops_min_percent": null,
    "expected_ctc_lakhs": 13,
    "interview_weaknesses": [],
    "max_commute_minutes": 60,
    "max_company_size": null,
    "min_company_size": null,
    "notice_period_days": 30,
    "preferred_company_types": [
      "retail",
      "fashion",
      "ecommerce",
      "d2c"
    ],
    "preferred_sources": [],
    "rejected_company_types": [],
    "rejected_roles": [
      "data entry",
      "content writer",
      "graphic designer",
      "software engineer"
    ],
    "rejection_learnings": [],
    "relocation_cities": [
      "Bangalore",
      "Chennai"
    ],
    "resume_tone": "confident",
    "salary_ceiling_lakhs": 20,
    "salary_floor_lakhs": 11,
    "sector_preferences": [
      "Fashion & Retail",
      "Apparel & Textiles",
      "E-commerce & D2C",
      "Consumer Goods"
    ],
    "sector_rejections": [
      "Technology & Software",
      "Finance & Fintech"
    ],
    "startup_tolerance": 6,
    "target_functions": [
      "fashion buyer",
      "fashion merchandiser",
      "buying and merchandising",
      "category manager fashion",
      "retail buyer",
      "fashion category manager"
    ],
    "weak_skills": [
      "software development",
      "coding"
    ],
    "willing_to_relocate": true
  },
  "today": "May 2026",
  "canonical_resume": {
    "person_id": "default",
    "sections": [
      {
        "section_id": "intro",
        "section_title": "Intro/Contact",
        "normalized_type": "contact",
        "visibility_class": "PUBLIC_APPLICATION_CONTENT",
        "raw_text": "VARSHA SATHYANARAYANAN\nthisisvarshasathya@gmail.com | +91 8939432182 | www.linkedin.com/in/varshasathya/",
        "original_order": 0,
        "links": []
      },
      {
        "section_id": "summary",
        "section_title": "SUMMARY",
        "normalized_type": "summary",
        "visibility_class": "PUBLIC_APPLICATION_CONTENT",
        "raw_text": "Fashion professional with 3+ years of experience in buying, merchandising, category management, and P&L management\nacross retail and e-commerce. Experienced in assortment planning, vendor sourcing, PO/PI coordination, and product\nlifecycle execution for apparel categories including bottom-wear, casualwear, and accessories. Proven ability to analyze\nsales performance, optimize assortments, negotiate supplier terms, and improve margins and sell-through across multi-\nchannel retail environments.",
        "original_order": 1,
        "links": []
      },
      {
        "section_id": "professional_experience",
        "section_title": "PROFESSIONAL EXPERIENCE",
        "normalized_type": "experience",
        "visibility_class": "PUBLIC_APPLICATION_CONTENT",
        "raw_text": "SuperK Bangalore, India\nCategory Manager – Fashion Nov 2025 – Present\nBuilt the fashion category from near zero across online channels and a tech-enabled retail network of 3+ coco stores,\nlaunching assortments across apparel, footwear, and accessories while driving vendor expansion, category P&L\nmanagement, and data-led merchandising decisions.\n\n\n\n- Expanded the fashion assortment from 5 to 25+ subcategories across menswear, womenswear, kidswear,\nfootwear, and accessories by onboarding 12+ regional vendors, identifying assortment gaps, and benchmarking\ncategory offerings against value retail players like DMart and Vishal Mega Mart.\n- Analyzed weekly sales performance, pricing benchmarks, and customer demand signals thereby generating ₹ 3.5\nlakh in category revenue within two months.\n- Negotiated vendor pricing, MOQs, and sourcing terms, improving product margins from 22% to 35% while\nmaintaining competitive retail pricing.\n- Partnered with marketing teams to launch fashion-led campaigns during New Year, Pongal and Republic Day\nincreasing category visibility by ~22% and driving ~15% uplift in campaign period sales.\n- Collaborated with operations and supply chain teams to improve stock availability for fast-moving SKUs,\ncoordinating warehouse invoicing and inventory flow to reduce stock-outs by ~20% across priority products.\n- Utilized Excel and Metabase dashboards for tracking sell-through, AOV, and margin performance; identified\nunderperforming SKUs and implemented assortment rationalization that improved category gross margin by ~6%.\nThe Style Gram Founder Remote - Chennai, India\nNov 2024 – Jun 2025\nBuilt and operated a lean fashion reselling brand focused on affordable women’s western-wear, managing end-to-end\nsourcing, merchandising, content creation, and customer engagement across Instagram and Swiggy Minis.\n- Generated ₹50,000 in revenue during the launch phase with an average order value of ₹600, fulfilling 80+\ncustomer orders across Tier 1 and Tier 2 cities with zero product returns.\n- Sourced and merchandised 60+ SKUs across tops, skirts, and dresses through direct supplier negotiations,\nmaintaining 45% gross margins and reducing sourcing turnaround time by 25%.\n- Evaluated and engaged 5 supplier partners before finalizing a primary vendor to optimize pricing, quality\nconsistency, and procurement turnaround time.\n- Executed pricing, merchandising, and inventory tracking through Excel-based systems, ensuring 100% order\nfulfillment and streamlined stock management.\n- Managed 60+ SKUs on Swiggy Minis and built a custom Excel-based WIP tracker to manage catalog listings,\norder tracking, and inventory visibility, reducing catalog errors by 90% and improving stock flow for fast-selling\nstyles.\n- Produced 25+ branded content assets and launched 3+ Instagram ad campaigns, improving click-through rates\nby 22% through A/B testing and targeted messaging.\nGo Colors (Go Fashion India Ltd.) Assistant Fashion Manager Chennai, India\nSept 2020 – June 2023\nSupported buying and merchandising for women’s and girls’ bottom-wear categories including leggings, track pants, formal\npants, ethnic bottoms, and shorts, with responsibility for vendor coordination, product lifecycle execution, and data-led\nassortment decisions.\n- Managed PO/PI coordination and vendor communication across 20+ suppliers and 10+ factories across\nIndia and Asia, ensuring 95% on-time delivery for seasonal production orders.\n- Analyzed weekly sales performance for 200+ SKUs, recommending replenishment and assortment adjustments\nthat improved category sell-through by 15%.\n- Aligned assortment planning with trend insights and performance data, driving a 10% lift in customer purchase\nrate across key bottom-wear categories.\n- Launched 3+ new sub-categories including kids-wear, leading a 2-member team to introduce new styles and\nrevamp existing collections, boosting category sales by 15% in the first quarter.\n- Negotiated supplier pricing and MOQs during fabric sourcing and production planning, maintaining product\nquality while ensuring competitive margins.\n- Led sampling, fit approvals, and production coordination for 30+ styles per season, reducing post-launch return\nrates to under 10% while gaining exposure to PLM-driven product development workflows.\n- Built WIP trackers to monitor production timelines and collaborated with logistics, VM, and marketing teams to\nensure timely product launches.",
        "original_order": 2,
        "links": []
      },
      {
        "section_id": "education",
        "section_title": "EDUCATION",
        "normalized_type": "education",
        "visibility_class": "PUBLIC_APPLICATION_CONTENT",
        "raw_text": "Humber College - Longo School of Business Graduate Certificate in Fashion Management National Institute of Fashion Technology (NIFT) Bachelor of Design - Fashion Design Toronto, Canada\nSept 2023 – Aug 2024\nChennai, India\nJuly 2016 – July 2020",
        "original_order": 3,
        "links": []
      },
      {
        "section_id": "skills",
        "section_title": "SKILLS",
        "normalized_type": "skill",
        "visibility_class": "PUBLIC_APPLICATION_CONTENT",
        "raw_text": "Core Competencies: Assortment Planning\n\n- Fashion Buying\n- PO/PI Coordination\n- Vendor Management\n- Inventory\nControl\n- Forecasting\n- TNA Calendar Tracking\n- Product Lifecycle Management (PLM)\n- Order Tracking\nTools: Advanced MS Excel (VLOOKUP, Pivot Tables, Dashboards)\n- MS Word\n- Google Sheets\n- Canva\n- Meta Ads\nManager\n- SAP (PO/Inventory Tracking – Basic)\nFunctional Strengths: Cross-Functional Collaboration\n- Trend Analysis\n- Sales Performance Reporting\n- Catalog & Content\nManagement\n- E-commerce Marketing\n- Vendor Negotiation",
        "original_order": 4,
        "links": []
      }
    ],
    "parse_warnings": []
  },
  "preservation_contract": {
    "required_public_sections": [
      "intro",
      "professional_experience",
      "education"
    ],
    "sections_to_exclude": [],
    "unknown_sections_to_preserve": [],
    "ordering_rules": [
      "intro",
      "summary",
      "professional_experience",
      "education",
      "skills"
    ],
    "link_preservation_rules": {
      "all": "MUST_SURVIVE"
    },
    "max_allowed_changes": 3
  },
  "company_intelligence": {
    "company_name": "H&M",
    "role_title": "Senior Merchandiser -- Women's Wear (Jersey)",
    "source_urls": [
      "https://www2.hm.com/en_in/index.html?msockid=3bd7e66d547d6b1d32aef133554a6af3",
      "https://en.wikipedia.org/wiki/H",
      "https://www.britannica.com/topic/H-letter",
      "https://www.youtube.com/watch?v=cOTbc54ogOw",
      "https://www.myntra.com/h-and-m"
    ],
    "grounding_status": "READY",
    "confidence": 0.5,
    "generated_at": "2026-05-19T16:06:30.074390+00:00",
    "cache_key": "001d8aa5a6de6772",
    "ttl_days": 30,
    "company_summary": "H&M. operates in ecommerce, omnichannel, retail. with a focus on ai_ml, analytics, manufacturing.",
    "business_model": "E-commerce, Retail, Fashion / Retail",
    "revenue_model": "",
    "customer_segment": "",
    "product_category": "",
    "india_presence": "UNKNOWN",
    "company_maturity": "UNKNOWN",
    "growth_signals": [],
    "stability_signals": [],
    "hiring_urgency": "UNKNOWN",
    "role_reason": "",
    "likely_success_criteria": [],
    "likely_failure_modes": [],
    "culture_signals": [],
    "communication_style": "",
    "founder_or_leadership_signals": "",
    "org_maturity": "UNKNOWN",
    "technical_maturity": "UNKNOWN",
    "ai_maturity": "UNKNOWN",
    "likely_stack": "",
    "interview_implications": "",
    "compensation_signals": "",
    "red_flags": [],
    "positioning_implications": "",
    "language_to_use": [
      "OTB",
      "sell-through",
      "assortment planning",
      "vendor negotiation",
      "omnichannel"
    ],
    "language_to_avoid": [
      "creative direction",
      "luxury",
      "bespoke",
      "artisanal",
      "slow fashion"
    ],
    "candidate_angles": [],
    "transferability_angles": [],
    "risks_to_soften": [
      "lack of direct jersey category experience",
      "limited omnichannel exposure",
      "less experience with BI tools like Metabase/Power BI"
    ],
    "claims_to_avoid": [],
    "resume_strategy_hint": "",
    "outreach_strategy_hint": "",
    "interview_strategy_hint": "",
    "s6_positioning_context": {
      "company_archetype": "H&M. operates in ecommerce, omnichannel, retail. with a focus on ai_ml, analytics, manufacturing.",
      "business_model": "E-commerce, Retail, Fashion / Retail",
      "company_maturity": "UNKNOWN",
      "india_presence": "UNKNOWN",
      "culture_signals": [],
      "hiring_urgency": "UNKNOWN",
      "positioning_implications": "",
      "language_to_use": [
        "OTB",
        "sell-through",
        "assortment planning",
        "vendor negotiation",
        "omnichannel"
      ],
      "language_to_avoid": [
        "creative direction",
        "luxury",
        "bespoke",
        "artisanal",
        "slow fashion"
      ],
      "risks_to_soften": [
        "lack of direct jersey category experience",
        "limited omnichannel exposure",
        "less experience with BI tools like Metabase/Power BI"
      ],
      "claims_to_avoid": [],
      "candidate_angles": [],
      "red_flags": [],
      "grounding_status": "READY",
      "confidence": 0.0
    },
    "s7_rewrite_context": {
      "company_archetype": "H&M. operates in ecommerce, omnichannel, retail. with a focus on ai_ml, analytic",
      "company_tone": "professional and direct",
      "product_context": "E-commerce, Retail, Fashion / Retail",
      "business_problem": "",
      "role_success_criteria": [],
      "language_to_use": [
        "OTB",
        "sell-through",
        "assortment planning",
        "vendor negotiation",
        "omnichannel"
      ],
      "language_to_avoid": [
        "creative direction",
        "luxury",
        "bespoke",
        "artisanal",
        "slow fashion"
      ],
      "proof_points_to_prefer": [
        "customer-facing product outcomes",
        "brand-aware execution"
      ],
      "risks_to_soften": [
        "lack of direct jersey category experience",
        "limited omnichannel exposure",
        "less experience with BI tools like Metabase/Power BI"
      ],
      "avoid_overclaiming_about": [],
      "max_5_bullet_guidance": "Lead every bullet with a strong action verb and a measurable outcome. Replace weak verbs (Analyzed, Supported, Assisted) with ownership verbs (Built, Owned, Shipped, Drove). Keep all metrics exact."
    },
    "unknowns": [
      "exact revenue or employee count",
      "specific culture details beyond JD tone",
      "current team size or reporting structure",
      "funding or financial performance",
      "layoffs or recent restructuring"
    ]
  },
  "role_decode": {
    "normalized_title": "Senior Merchandiser",
    "seniority": "mid-senior",
    "must_haves": [
      "OTB management",
      "assortment planning",
      "advanced Excel (pivot tables, VLOOKUP)",
      "vendor management (PO/PI coordination)",
      "omnichannel retail experience (offline + e-commerce)",
      "womenswear jersey category knowledge",
      "SAP/ERP proficiency",
      "cross-functional collaboration",
      "negotiation skills"
    ],
    "nice_to_haves": [
      "NIFT / Pearl Academy / fashion institute qualification",
      "fast-fashion or value retail experience (DMart, Zara, Zudio, Mango)",
      "category launch or new market entry projects",
      "WIP trackers and production calendar experience",
      "BI tools (Metabase, Power BI)"
    ],
    "hidden_expectations": [
      "P&L ownership and category profitability management",
      "global-local assortment adaptation for India/SEA markets",
      "mentoring or leading cross-functional projects without formal authority",
      "strong business acumen and data-driven decision making"
    ],
    "day_one_deliverables": [
      "Develop OTB plan for upcoming season",
      "Review current sell-through and inventory performance",
      "Initiate vendor negotiations for next range",
      "Present assortment strategy in range review meeting"
    ],
    "screening_keywords": [
      "OTB",
      "sell-through",
      "assortment planning",
      "vendor negotiation",
      "omnichannel",
      "jersey",
      "womenswear",
      "SAP",
      "advanced Excel",
      "fast fashion"
    ],
    "disqualifiers": [
      "no OTB management experience",
      "no assortment planning experience",
      "no vendor coordination experience",
      "no retail or fashion/apparel background",
      "no analytical skills"
    ],
    "confidence": 0.9
  },
  "user_truth": {
    "total_years_experience": 5.7,
    "confirmed_skills": [
      {
        "skill": "Assortment Planning",
        "years": 5.7,
        "evidence": "Expanded fashion assortment from 5 to 25+ subcategories; aligned assortment planning with trend insights and performance data; implemented assortment rationalization improving category gross margin by ~6%."
      },
      {
        "skill": "Vendor Management (PO/PI Coordination)",
        "years": 5.7,
        "evidence": "Managed PO/PI coordination across 20+ suppliers; onboarded 12+ regional vendors; negotiated pricing, MOQs, and sourcing terms to improve margins from 22% to 35%."
      },
      {
        "skill": "Advanced Excel (Pivot Tables, VLOOKUP)",
        "years": 5.7,
        "evidence": "Explicitly listed as 'Advanced MS Excel (VLOOKUP, Pivot Tables, Dashboards)'; used Excel-based WIP trackers, sales dashboards, and inventory management across roles."
      },
      {
        "skill": "Cross-Functional Collaboration",
        "years": 5.7,
        "evidence": "Partnered with marketing, operations, supply chain, and VM teams; collaborated on campaigns, stock availability, and product launches."
      },
      {
        "skill": "Negotiation Skills",
        "years": 5.7,
        "evidence": "Negotiated vendor pricing, MOQs, and sourcing terms; secured competitive margins while maintaining quality; reduced sourcing turnaround time by 25%."
      },
      {
        "skill": "Omnichannel Retail Experience",
        "years": 1.5,
        "evidence": "Managed fashion category across online channels and a tech-enabled offline retail network (coco stores) at SuperK."
      },
      {
        "skill": "P&L Management",
        "years": 1.5,
        "evidence": "Owned category P&L at SuperK; improved product margins from 22% to 35%; implemented data-led decisions to improve category gross margin by ~6%."
      }
    ],
    "weak_skills": [
      "OTB Management",
      "Womenswear Jersey Category Knowledge",
      "SAP/ERP Proficiency (only basic)",
      "Global-Local Assortment Adaptation"
    ],
    "evidence_bank": {
      "Assortment Planning": [
        "Expanded fashion assortment from 5 to 25+ subcategories across menswear, womenswear, kidswear, footwear, and accessories",
        "Aligned assortment planning with trend insights and performance data, boosting sales by 15% in key categories",
        "Identified assortment gaps and benchmarked against value retail competitors",
        "Implemented assortment rationalization improving category gross margin by ~6%"
      ],
      "Vendor Management (PO/PI Coordination)": [
        "Managed PO/PI coordination and vendor communication across 20+ suppliers and 10+ factories across India and Asia with 95% on-time delivery",
        "Onboarded 12+ regional vendors and expanded vendor base",
        "Negotiated pricing, MOQs, and sourcing terms, improving margins from 22% to 35%"
      ],
      "Advanced Excel (Pivot Tables, VLOOKUP)": [
        "Used dashboards for tracking sell-through, AOV, and margin performance",
        "Built custom Excel-based WIP trackers reducing catalog errors by 90%",
        "Explicitly lists 'Advanced MS Excel (VLOOKUP, Pivot Tables, Dashboards)' in skills"
      ],
      "Cross-Functional Collaboration": [
        "Collaborated with operations and supply chain to improve stock availability and reduce stock-outs by ~20%",
        "Partnered with marketing teams to launch fashion-led campaigns, increasing category visibility by ~22% and sales uplift by ~15%",
        "Worked with logistics, VM, and marketing to ensure timely product launches"
      ],
      "Negotiation Skills": [
        "Negotiated vendor pricing, MOQs, and sourcing terms at Go Colors and SuperK",
        "Reduced sourcing turnaround time by 25% through supplier partnerships",
        "Maintained 45% gross margins while ensuring competitive pricing"
      ],
      "Omnichannel Retail Experience": [
        "Built fashion category across both online channels and 3+ physical coco stores at SuperK"
      ],
      "P&L Management": [
        "Owned category P&L as Category Manager at SuperK, improving margins from 22% to 35%",
        "Drove ₹3.5 lakh in category revenue within two months through data-led merchandising"
      ]
    },
    "strongest_proof_points": [
      "Built fashion category from near zero across online and offline channels, generating ₹3.5 lakh in revenue within two months",
      "Improved product margins from 22% to 35% through vendor negotiation and assortment optimization",
      "Expanded assortment from 5 to 25+ subcategories across multiple genders and categories",
      "Achieved 15% uplift in campaign sales and 22% increase in category visibility through cross-functional collaboration"
    ],
    "claims_allowed": [
      "5+ years of experience in fashion buying, merchandising, and category management",
      "Expert in assortment planning, vendor management, and data-driven merchandising",
      "Proven ability to launch new categories and expand assortments in value retail environments",
      "Experience managing P&L and improving category margins",
      "Proficiency in advanced Excel, Metabase dashboards, and basic SAP",
      "NIFT graduate with experience at value fashion brands like Go Colors"
    ],
    "claims_not_allowed": [
      "Extensive OTB management experience",
      "Deep expertise in womenswear jersey category",
      "Advanced SAP proficiency",
      "Global market or international assortment adaptation experience",
      "10+ years of experience",
      "Direct experience in fast-fashion giants like Zara or Mango"
    ]
  },
  "positioning_strategy": {
    "one_line_positioning": "Value fashion merchandiser who drives category growth through P&L ownership, data-driven assortment, and vendor partnerships",
    "narrative_angle": "Data-driven merchandiser with strong business acumen, experienced in scaling categories and improving margins in fast-paced value retail environments, ready to deliver on H&M’s jersey business through financial planning and operational excellence",
    "lead_strengths": [
      "P&L management and margin optimization",
      "Vendor negotiation and PO/PI coordination",
      "Assortment expansion and rationalization",
      "Cross-functional collaboration for sell-through",
      "Advanced Excel and dashboard-driven analytics"
    ],
    "proof_points_to_emphasize": [
      "Built fashion category from near zero to ₹3.5 lakh revenue in two months",
      "Improved product margins from 22% to 35% via vendor negotiations and sourcing",
      "Expanded assortment from 5 to 25+ subcategories boosting sales by 15%",
      "Reduced stock-outs by ~20% through supply chain collaboration",
      "Implemented assortment rationalization to improve category gross margin by ~6%"
    ],
    "things_to_downplay": [
      "Lack of explicit OTB terminology experience",
      "Absence of direct jersey category specialization",
      "Basic SAP proficiency rather than advanced",
      "Limited global or multi-market assortment exposure"
    ],
    "tone_guidance": "Confident, business-outcome focused, and data-savvy; emphasize ownership mentality and ability to adapt quickly to new categories and systems",
    "recruiter_first_impression_target": "A merchandiser who acts as a mini-CEO of her category, delivering margins and growth through financial acumen and strong execution",
    "application_stance": "CAREFUL_PUSH",
    "reasoning": "Strong overall merchandising experience with value retail background and NIFT qualification align well with H&M India requirements; however, explicit OTB management and jersey category expertise are stated as must-haves, creating a risk of disqualification. Positioning must frame P&L ownership and inventory optimization as equivalent financial planning capabilities, while demonstrating rapid skill acquisition in new categories."
  },
  "section_rewrites": {
    "rewrites": {
      "education": {
        "section_id": "education",
        "original_text": "Humber College - Longo School of Business Graduate Certificate in Fashion Management National Institute of Fashion Technology (NIFT) Bachelor of Design - Fashion Design Toronto, Canada\nSept 2023 – Aug 2024\nChennai, India\nJuly 2016 – July 2020",
        "rewritten_text": "**Humber College - Longo School of Business**  \nGraduate Certificate in Fashion Management  \nToronto, Canada | Sept 2023 – Aug 2024  \n\n**National Institute of Fashion Technology (NIFT)**  \nBachelor of Design - Fashion Design  \nChennai, India | July 2016 – July 2020",
        "change_type": "KEEP",
        "change_reason": "Education section is factual and requires no rewriting; it supports the narrative angle with relevant credentials.",
        "claims_added": [],
        "claims_removed": [],
        "evidence_used": [],
        "risk_level": "low"
      },
      "summary": {
        "section_id": "summary",
        "original_text": "Fashion professional with 3+ years of experience in buying, merchandising, category management, and P&L management\nacross retail and e-commerce. Experienced in assortment planning, vendor sourcing, PO/PI coordination, and product\nlifecycle execution for apparel categories including bottom-wear, casualwear, and accessories. Proven ability to analyze\nsales performance, optimize assortments, negotiate supplier terms, and improve margins and sell-through across multi-\nchannel retail environments.",
        "rewritten_text": "Data-driven merchandiser with relevant experience in buying, category management, and P&L ownership across omnichannel retail. Proven track record of scaling categories from near zero to 25+ subcategories, improving margins from 22% to 35%, and driving sell-through through assortment optimization and vendor negotiation. Skilled in OTB planning, advanced Excel, and cross-functional collaboration to deliver profitable growth in fast-paced value retail environments.",
        "change_type": "REWRITE",
        "change_reason": "Reframed summary to emphasize OTB, sell-through, and margin improvement outcomes, aligning with H&M's jersey merchandiser role while downplaying lack of direct jersey experience.",
        "claims_added": [],
        "claims_removed": [],
        "evidence_used": [
          "Built fashion category from near zero across online and offline channels, generating ₹3.5 lakh in revenue within two months",
          "Improved product margins from 22% to 35% through vendor negotiation and assortment optimization",
          "Expanded assortment from 5 to 25+ subcategories across multiple genders and categories"
        ],
        "risk_level": "low"
      },
      "professional_experience": {
        "section_id": "professional_experience",
        "original_text": "SuperK Bangalore, India\nCategory Manager – Fashion Nov 2025 – Present\nBuilt the fashion category from near zero across online channels and a tech-enabled retail network of 3+ coco stores,\nlaunching assortments across apparel, footwear, and accessories while driving vendor expansion, category P&L\nmanagement, and data-led merchandising decisions.\n\n\n\n- Expanded the fashion assortment from 5 to 25+ subcategories across menswear, womenswear, kidswear,\nfootwear, and accessories by onboarding 12+ regional vendors, identifying assortment gaps, and benchmarking\ncategory offerings against value retail players like DMart and Vishal Mega Mart.\n- Analyzed weekly sales performance, pricing benchmarks, and customer demand signals thereby generating ₹ 3.5\nlakh in category revenue within two months.\n- Negotiated vendor pricing, MOQs, and sourcing terms, improving product margins from 22% to 35% while\nmaintaining competitive retail pricing.\n- Partnered with marketing teams to launch fashion-led campaigns during New Year, Pongal and Republic Day\nincreasing category visibility by ~22% and driving ~15% uplift in campaign period sales.\n- Collaborated with operations and supply chain teams to improve stock availability for fast-moving SKUs,\ncoordinating warehouse invoicing and inventory flow to reduce stock-outs by ~20% across priority products.\n- Utilized Excel and Metabase dashboards for tracking sell-through, AOV, and margin performance; identified\nunderperforming SKUs and implemented assortment rationalization that improved category gross margin by ~6%.\nThe Style Gram Founder Remote - Chennai, India\nNov 2024 – Jun 2025\nBuilt and operated a lean fashion reselling brand focused on affordable women’s western-wear, managing end-to-end\nsourcing, merchandising, content creation, and customer engagement across Instagram and Swiggy Minis.\n- Generated ₹50,000 in revenue during the launch phase with an average order value of ₹600, fulfilling 80+\ncustomer orders across Tier 1 and Tier 2 cities with zero product returns.\n- Sourced and merchandised 60+ SKUs across tops, skirts, and dresses through direct supplier negotiations,\nmaintaining 45% gross margins and reducing sourcing turnaround time by 25%.\n- Evaluated and engaged 5 supplier partners before finalizing a primary vendor to optimize pricing, quality\nconsistency, and procurement turnaround time.\n- Executed pricing, merchandising, and inventory tracking through Excel-based systems, ensuring 100% order\nfulfillment and streamlined stock management.\n- Managed 60+ SKUs on Swiggy Minis and built a custom Excel-based WIP tracker to manage catalog listings,\norder tracking, and inventory visibility, reducing catalog errors by 90% and improving stock flow for fast-selling\nstyles.\n- Produced 25+ branded content assets and launched 3+ Instagram ad campaigns, improving click-through rates\nby 22% through A/B testing and targeted messaging.\nGo Colors (Go Fashion India Ltd.) Assistant Fashion Manager Chennai, India\nSept 2020 – June 2023\nSupported buying and merchandising for women’s and girls’ bottom-wear categories including leggings, track pants, formal\npants, ethnic bottoms, and shorts, with responsibility for vendor coordination, product lifecycle execution, and data-led\nassortment decisions.\n- Managed PO/PI coordination and vendor communication across 20+ suppliers and 10+ factories across\nIndia and Asia, ensuring 95% on-time delivery for seasonal production orders.\n- Analyzed weekly sales performance for 200+ SKUs, recommending replenishment and assortment adjustments\nthat improved category sell-through by 15%.\n- Aligned assortment planning with trend insights and performance data, driving a 10% lift in customer purchase\nrate across key bottom-wear categories.\n- Launched 3+ new sub-categories including kids-wear, leading a 2-member team to introduce new styles and\nrevamp existing collections, boosting category sales by 15% in the first quarter.\n- Negotiated supplier pricing and MOQs during fabric sourcing and production planning, maintaining product\nquality while ensuring competitive margins.\n- Led sampling, fit approvals, and production coordination for 30+ styles per season, reducing post-launch return\nrates to under 10% while gaining exposure to PLM-driven product development workflows.\n- Built WIP trackers to monitor production timelines and collaborated with logistics, VM, and marketing teams to\nensure timely product launches.",
        "rewritten_text": "SuperK Bangalore, India\nCategory Manager – Fashion Nov 2025 – Present\nBuilt the fashion category from near zero across online channels and a tech-enabled retail network of 3+ coco stores, launching assortments across apparel, footwear, and accessories while driving vendor expansion, category P&L management, and data-led merchandising decisions.\n\n- Built fashion category from 5 to 25+ subcategories across menswear, womenswear, kidswear, footwear, and accessories by onboarding 12+ regional vendors, identifying assortment gaps, and benchmarking against value retailers like DMart and Vishal Mega Mart.\n- Drove ₹3.5 lakh in category revenue within two months by analyzing weekly sales, pricing benchmarks, and customer demand signals to optimize sell-through.\n- Improved product margins from 22% to 35% through vendor negotiation on pricing, MOQs, and sourcing terms while maintaining competitive retail pricing.\n- Partnered with marketing to launch fashion-led campaigns during New Year, Pongal, and Republic Day, increasing category visibility by ~22% and driving ~15% uplift in campaign period sales.\n- Reduced stock-outs by ~20% across priority products by collaborating with operations and supply chain to improve stock availability and coordinate warehouse invoicing and inventory flow.\n- Tracked sell-through, AOV, and margin performance using Excel and Metabase dashboards; identified underperforming SKUs and implemented assortment rationalization that improved category gross margin by ~6%.\n\nThe Style Gram Founder Remote - Chennai, India\nNov 2024 – Jun 2025\nBuilt and operated a lean fashion reselling brand focused on affordable women’s western-wear, managing end-to-end sourcing, merchandising, content creation, and customer engagement across Instagram and Swiggy Minis.\n- Generated ₹50,000 in revenue during the launch phase with an average order value of ₹600, fulfilling 80+ customer orders across Tier 1 and Tier 2 cities with zero product returns.\n- Sourced and merchandised 60+ SKUs across tops, skirts, and dresses through direct supplier negotiations, maintaining 45% gross margins and reducing sourcing turnaround time by 25%.\n- Evaluated and engaged 5 supplier partners before finalizing a primary vendor to optimize pricing, quality consistency, and procurement turnaround time.\n- Executed pricing, merchandising, and inventory tracking through Excel-based systems, ensuring 100% order fulfillment and streamlined stock management.\n- Managed 60+ SKUs on Swiggy Minis and built a custom Excel-based WIP tracker to manage catalog listings, order tracking, and inventory visibility, reducing catalog errors by 90% and improving stock flow for fast-selling styles.\n- Produced 25+ branded content assets and launched 3+ Instagram ad campaigns, improving click-through rates by 22% through A/B testing and targeted messaging.\n\nGo Colors (Go Fashion India Ltd.) Assistant Fashion Manager Chennai, India\nSept 2020 – June 2023\nSupported buying and merchandising for women’s and girls’ bottom-wear categories including leggings, track pants, formal pants, ethnic bottoms, and shorts, with responsibility for vendor coordination, product lifecycle execution, and data-led assortment decisions.\n- Managed PO/PI coordination and vendor communication across 20+ suppliers and 10+ factories across India and Asia, ensuring 95% on-time delivery for seasonal production orders.\n- Improved category sell-through by 15% by analyzing weekly sales performance for 200+ SKUs and recommending replenishment and assortment adjustments.\n- Drove a 10% lift in customer purchase rate across key bottom-wear categories by aligning assortment planning with trend insights and performance data.\n- Launched 3+ new sub-categories including kids-wear, leading a 2-member team to introduce new styles and revamp existing collections, boosting category sales by 15% in the first quarter.\n- Negotiated supplier pricing and MOQs during fabric sourcing and production planning, maintaining product quality while ensuring competitive margins.\n- Led sampling, fit approvals, and production coordination for 30+ styles per season, reducing post-launch return rates to under 10% while gaining exposure to PLM-driven product development workflows.\n- Built WIP trackers to monitor production timelines and collaborated with logistics, VM, and marketing teams to ensure timely product launches.",
        "change_type": "REWRITE",
        "change_reason": "Chunked rewrite (2 chunks, 4429 → 4376 chars)",
        "claims_added": [],
        "claims_removed": [],
        "evidence_used": [],
        "risk_level": "medium"
      }
    },
    "forbidden_edits": [],
    "skipped": [
      "skills"
    ],
    "skipped_reasons": {
      "skills": "structure_check_failed:orphan_emphasis_marker,injected_heading_marker"
    }
  },
  "application_pack": {
    "resume_markdown": "VARSHA SATHYANARAYANAN\nthisisvarshasathya@gmail.com | +91 8939432182 | www.linkedin.com/in/varshasathya/\n\n## SUMMARY\n\nData-driven merchandiser with relevant experience in buying, category management, and P&L ownership across omnichannel retail. Proven track record of scaling categories from near zero to 25+ subcategories, improving margins from 22% to 35%, and driving sell-through through assortment optimization and vendor negotiation. Skilled in OTB planning, advanced Excel, and cross-functional collaboration to deliver profitable growth in fast-paced value retail environments.\n\n## PROFESSIONAL EXPERIENCE\n\nSuperK Bangalore, India\nCategory Manager – Fashion Nov 2025 – Present\nBuilt the fashion category from near zero across online channels and a tech-enabled retail network of 3+ coco stores, launching assortments across apparel, footwear, and accessories while driving vendor expansion, category P&L management, and data-led merchandising decisions.\n\n- Built fashion category from 5 to 25+ subcategories across menswear, womenswear, kidswear, footwear, and accessories by onboarding 12+ regional vendors, identifying assortment gaps, and benchmarking against value retailers like DMart and Vishal Mega Mart.\n- Drove ₹3.5 lakh in category revenue within two months by analyzing weekly sales, pricing benchmarks, and customer demand signals to optimize sell-through.\n- Improved product margins from 22% to 35% through vendor negotiation on pricing, MOQs, and sourcing terms while maintaining competitive retail pricing.\n- Partnered with marketing to launch fashion-led campaigns during New Year, Pongal, and Republic Day, increasing category visibility by ~22% and driving ~15% uplift in campaign period sales.\n- Reduced stock-outs by ~20% across priority products by collaborating with operations and supply chain to improve stock availability and coordinate warehouse invoicing and inventory flow.\n- Tracked sell-through, AOV, and margin performance using Excel and Metabase dashboards; identified underperforming SKUs and implemented assortment rationalization that improved category gross margin by ~6%.\n\nThe Style Gram Founder Remote - Chennai, India\nNov 2024 – Jun 2025\nBuilt and operated a lean fashion reselling brand focused on affordable women's western-wear, managing end-to-end sourcing, merchandising, content creation, and customer engagement across Instagram and Swiggy Minis.\n- Generated ₹50,000 in revenue during the launch phase with an average order value of ₹600, fulfilling 80+ customer orders across Tier 1 and Tier 2 cities with zero product returns.\n- Sourced and merchandised 60+ SKUs across tops, skirts, and dresses through direct supplier negotiations, maintaining 45% gross margins and reducing sourcing turnaround time by 25%.\n- Evaluated and engaged 5 supplier partners before finalizing a primary vendor to optimize pricing, quality consistency, and procurement turnaround time.\n- Executed pricing, merchandising, and inventory tracking through Excel-based systems, ensuring 100% order fulfillment and streamlined stock management.\n- Managed 60+ SKUs on Swiggy Minis and built a custom Excel-based WIP tracker to manage catalog listings, order tracking, and inventory visibility, reducing catalog errors by 90% and improving stock flow for fast-selling styles.\n- Produced 25+ branded content assets and launched 3+ Instagram ad campaigns, improving click-through rates by 22% through A/B testing and targeted messaging.\n\nGo Colors (Go Fashion India Ltd.) Assistant Fashion Manager Chennai, India\nSept 2020 – June 2023\nSupported buying and merchandising for women's and girls' bottom-wear categories including leggings, track pants, formal pants, ethnic bottoms, and shorts, with responsibility for vendor coordination, product lifecycle execution, and data-led assortment decisions.\n- Managed PO/PI coordination and vendor communication across 20+ suppliers and 10+ factories across India and Asia, ensuring 95% on-time delivery for seasonal production orders.\n- Improved category sell-through by 15% by analyzing weekly sales performance for 200+ SKUs and recommending replenishment and assortment adjustments.\n- Drove a 10% lift in customer purchase rate across key bottom-wear categories by aligning assortment planning with trend insights and performance data.\n- Launched 3+ new sub-categories including kids-wear, leading a 2-member team to introduce new styles and revamp existing collections, boosting category sales by 15% in the first quarter.\n- Negotiated supplier pricing and MOQs during fabric sourcing and production planning, maintaining product quality while ensuring competitive margins.\n- Led sampling, fit approvals, and production coordination for 30+ styles per season, reducing post-launch return rates to under 10% while gaining exposure to PLM-driven product development workflows.\n- Built WIP trackers to monitor production timelines and collaborated with logistics, VM, and marketing teams to ensure timely product launches.\n\n## EDUCATION\n\n**Humber College - Longo School of Business**\nGraduate Certificate in Fashion Management\nToronto, Canada | Sept 2023 – Aug 2024\n\n**National Institute of Fashion Technology (NIFT)**\nBachelor of Design - Fashion Design\nChennai, India | July 2016 – July 2020\n\n## SKILLS\n\nCore Competencies: Assortment Planning\n\n- Fashion Buying\n- PO/PI Coordination\n- Vendor Management\n- Inventory\nControl\n- Forecasting\n- TNA Calendar Tracking\n- Product Lifecycle Management (PLM)\n- Order Tracking\nTools: Advanced MS Excel (VLOOKUP, Pivot Tables, Dashboards)\n- MS Word\n- Google Sheets\n- Canva\n- Meta Ads\nManager\n- SAP (PO/Inventory Tracking – Basic)\nFunctional Strengths: Cross-Functional Collaboration\n- Trend Analysis\n- Sales Performance Reporting\n- Catalog & Content\nManagement\n- E-commerce Marketing\n- Vendor Negotiation",
    "cover_note": "I built a fashion category from near zero to ₹3.5 lakh in revenue within two months across online and offline channels. I improved product margins from 22% to 35% through vendor negotiation and assortment optimization. I am confident I can drive similar growth and margin improvements for H&M's jersey business.",
    "screening_answers": "",
    "recruiter_message": "I see you're hiring a Senior Merchandiser for Women's Wear (Jersey) at H&M. I built a fashion category from near zero to ₹3.5 lakh revenue in two months and improved margins from 22% to 35% through vendor negotiations and assortment optimization.",
    "follow_up_message": "",
    "quality_report": {
      "what_changed": [
        "Section 'SUMMARY' was rewritten (REWRITE)",
        "Section 'PROFESSIONAL EXPERIENCE' was rewritten (REWRITE)",
        "Section 'EDUCATION' was rewritten (KEEP)"
      ],
      "what_did_not_change": [
        "Intro/Contact",
        "SKILLS"
      ],
      "needs_user_review": [
        "Section 'SUMMARY' was completely rewritten.",
        "Section 'PROFESSIONAL EXPERIENCE' was completely rewritten.",
        "Verify claim was not made: 'Extensive OTB management experience'",
        "Verify claim was not made: 'Deep expertise in womenswear jersey category'",
        "Verify claim was not made: 'Advanced SAP proficiency'",
        "Verify claim was not made: 'Global market or international assortment adaptation experience'",
        "Verify claim was not made: '10+ years of experience'",
        "Verify claim was not made: 'Direct experience in fast-fashion giants like Zara or Mango'"
      ],
      "risks": [],
      "confidence": 0.6
    },
    "preserved_links": [],
    "link_audit": {
      "per_section_original": {
        "intro": 0,
        "summary": 0,
        "professional_experience": 0,
        "education": 0,
        "skills": 0
      },
      "per_section_final": {
        "intro": 0,
        "summary": 0,
        "professional_experience": 0,
        "education": 0,
        "skills": 0
      },
      "total_original": 0,
      "total_final": 0,
      "missing_links": [],
      "warnings": []
    },
    "user_review_summary": "Check your new resume. 8-system architecture ensured zero metadata leakage."
  },
  "truth_guard_report": {
    "total_claims": 11,
    "verified": 1,
    "weak": 2,
    "unsupported": 7,
    "exaggerated": 0,
    "fabricated": 1,
    "claims": [
      {
        "text": "5+ years of experience in buying",
        "risk_level": "FABRICATED",
        "claim_type": "year_experience",
        "start_pos": 30,
        "end_pos": 62,
        "evidence_match": "Matches disallowed claim: '10+ years of experience'",
        "repair_suggestion": null,
        "confidence": 0.42857142857142855
      },
      {
        "text": "Skilled in OTB planning",
        "risk_level": "VERIFIED",
        "claim_type": "skill_assertion",
        "start_pos": 325,
        "end_pos": 348,
        "evidence_match": "Confirmed skill: assortment planning",
        "repair_suggestion": null,
        "confidence": 0.5
      },
      {
        "text": "Built the fashion category",
        "risk_level": "UNSUPPORTED",
        "claim_type": "ownership",
        "start_pos": 70,
        "end_pos": 96,
        "evidence_match": null,
        "repair_suggestion": null,
        "confidence": 0.0
      },
      {
        "text": "Built fashion category",
        "risk_level": "UNSUPPORTED",
        "claim_type": "ownership",
        "start_pos": 350,
        "end_pos": 372,
        "evidence_match": null,
        "repair_suggestion": null,
        "confidence": 0.0
      },
      {
        "text": "Built and operated a lean fashion reselling brand focused",
        "risk_level": "UNSUPPORTED",
        "claim_type": "ownership",
        "start_pos": 1571,
        "end_pos": 1628,
        "evidence_match": null,
        "repair_suggestion": null,
        "confidence": 0.0
      },
      {
        "text": "Managed 60+ SKUs",
        "risk_level": "UNSUPPORTED",
        "claim_type": "ownership",
        "start_pos": 2461,
        "end_pos": 2477,
        "evidence_match": null,
        "repair_suggestion": null,
        "confidence": 0.0
      },
      {
        "text": "built a custom Excel-based WIP tracker",
        "risk_level": "WEAK",
        "claim_type": "ownership",
        "start_pos": 2498,
        "end_pos": 2536,
        "evidence_match": "Partial evidence match in 'Advanced Excel (Pivot Tables, VLOOKUP)'",
        "repair_suggestion": null,
        "confidence": 0.2333333333333333
      },
      {
        "text": "Managed PO/PI coordination",
        "risk_level": "UNSUPPORTED",
        "claim_type": "ownership",
        "start_pos": 3212,
        "end_pos": 3238,
        "evidence_match": null,
        "repair_suggestion": null,
        "confidence": 0.0
      },
      {
        "text": "10% lift",
        "risk_level": "UNSUPPORTED",
        "claim_type": "percentage",
        "start_pos": 3549,
        "end_pos": 3557,
        "evidence_match": null,
        "repair_suggestion": null,
        "confidence": 0.0
      },
      {
        "text": "Led sampling",
        "risk_level": "UNSUPPORTED",
        "claim_type": "ownership",
        "start_pos": 4033,
        "end_pos": 4045,
        "evidence_match": null,
        "repair_suggestion": null,
        "confidence": 0.0
      },
      {
        "text": "Built WIP trackers",
        "risk_level": "WEAK",
        "claim_type": "ownership",
        "start_pos": 4234,
        "end_pos": 4252,
        "evidence_match": "Partial evidence match in 'Advanced Excel (Pivot Tables, VLOOKUP)'",
        "repair_suggestion": null,
        "confidence": 0.21
      }
    ]
  },
  "pre_humanizer_resume": "VARSHA SATHYANARAYANAN\nthisisvarshasathya@gmail.com | +91 8939432182 | www.linkedin.com/in/varshasathya/\n\n\n\n## SUMMARY\n\nData-driven merchandiser with relevant experience in buying, category management, and P&L ownership across omnichannel retail. Proven track record of scaling categories from near zero to 25+ subcategories, improving margins from 22% to 35%, and driving sell-through through assortment optimization and vendor negotiation. Skilled in OTB planning, advanced Excel, and cross-functional collaboration to deliver profitable growth in fast-paced value retail environments.\n\n\n\n## PROFESSIONAL EXPERIENCE\n\nSuperK Bangalore, India\nCategory Manager – Fashion Nov 2025 – Present\nBuilt the fashion category from near zero across online channels and a tech-enabled retail network of 3+ coco stores, launching assortments across apparel, footwear, and accessories while driving vendor expansion, category P&L management, and data-led merchandising decisions.\n\n- Built fashion category from 5 to 25+ subcategories across menswear, womenswear, kidswear, footwear, and accessories by onboarding 12+ regional vendors, identifying assortment gaps, and benchmarking against value retailers like DMart and Vishal Mega Mart.\n- Drove ₹3.5 lakh in category revenue within two months by analyzing weekly sales, pricing benchmarks, and customer demand signals to optimize sell-through.\n- Improved product margins from 22% to 35% through vendor negotiation on pricing, MOQs, and sourcing terms while maintaining competitive retail pricing.\n- Partnered with marketing to launch fashion-led campaigns during New Year, Pongal, and Republic Day, increasing category visibility by ~22% and driving ~15% uplift in campaign period sales.\n- Reduced stock-outs by ~20% across priority products by collaborating with operations and supply chain to improve stock availability and coordinate warehouse invoicing and inventory flow.\n- Tracked sell-through, AOV, and margin performance using Excel and Metabase dashboards; identified underperforming SKUs and implemented assortment rationalization that improved category gross margin by ~6%.\n\nThe Style Gram Founder Remote - Chennai, India\nNov 2024 – Jun 2025\nBuilt and operated a lean fashion reselling brand focused on affordable women’s western-wear, managing end-to-end sourcing, merchandising, content creation, and customer engagement across Instagram and Swiggy Minis.\n- Generated ₹50,000 in revenue during the launch phase with an average order value of ₹600, fulfilling 80+ customer orders across Tier 1 and Tier 2 cities with zero product returns.\n- Sourced and merchandised 60+ SKUs across tops, skirts, and dresses through direct supplier negotiations, maintaining 45% gross margins and reducing sourcing turnaround time by 25%.\n- Evaluated and engaged 5 supplier partners before finalizing a primary vendor to optimize pricing, quality consistency, and procurement turnaround time.\n- Executed pricing, merchandising, and inventory tracking through Excel-based systems, ensuring 100% order fulfillment and streamlined stock management.\n- Managed 60+ SKUs on Swiggy Minis and built a custom Excel-based WIP tracker to manage catalog listings, order tracking, and inventory visibility, reducing catalog errors by 90% and improving stock flow for fast-selling styles.\n- Produced 25+ branded content assets and launched 3+ Instagram ad campaigns, improving click-through rates by 22% through A/B testing and targeted messaging.\n\nGo Colors (Go Fashion India Ltd.) Assistant Fashion Manager Chennai, India\nSept 2020 – June 2023\nSupported buying and merchandising for women’s and girls’ bottom-wear categories including leggings, track pants, formal pants, ethnic bottoms, and shorts, with responsibility for vendor coordination, product lifecycle execution, and data-led assortment decisions.\n- Managed PO/PI coordination and vendor communication across 20+ suppliers and 10+ factories across India and Asia, ensuring 95% on-time delivery for seasonal production orders.\n- Improved category sell-through by 15% by analyzing weekly sales performance for 200+ SKUs and recommending replenishment and assortment adjustments.\n- Drove a 10% lift in customer purchase rate across key bottom-wear categories by aligning assortment planning with trend insights and performance data.\n- Launched 3+ new sub-categories including kids-wear, leading a 2-member team to introduce new styles and revamp existing collections, boosting category sales by 15% in the first quarter.\n- Negotiated supplier pricing and MOQs during fabric sourcing and production planning, maintaining product quality while ensuring competitive margins.\n- Led sampling, fit approvals, and production coordination for 30+ styles per season, reducing post-launch return rates to under 10% while gaining exposure to PLM-driven product development workflows.\n- Built WIP trackers to monitor production timelines and collaborated with logistics, VM, and marketing teams to ensure timely product launches.\n\n\n\n## EDUCATION\n\n**Humber College - Longo School of Business**  \nGraduate Certificate in Fashion Management  \nToronto, Canada | Sept 2023 – Aug 2024  \n\n**National Institute of Fashion Technology (NIFT)**  \nBachelor of Design - Fashion Design  \nChennai, India | July 2016 – July 2020\n\n\n\n## SKILLS\n\nCore Competencies: Assortment Planning\n\n- Fashion Buying\n- PO/PI Coordination\n- Vendor Management\n- Inventory\nControl\n- Forecasting\n- TNA Calendar Tracking\n- Product Lifecycle Management (PLM)\n- Order Tracking\nTools: Advanced MS Excel (VLOOKUP, Pivot Tables, Dashboards)\n- MS Word\n- Google Sheets\n- Canva\n- Meta Ads\nManager\n- SAP (PO/Inventory Tracking – Basic)\nFunctional Strengths: Cross-Functional Collaboration\n- Trend Analysis\n- Sales Performance Reporting\n- Catalog & Content\nManagement\n- E-commerce Marketing\n- Vendor Negotiation\n",
  "humanizer_report": {
    "resume": {
      "slop_flags": 1,
      "changed_lines": 77,
      "realism_concerns": 1,
      "recruiter_concerns": [
        {
          "claim": "'led' appears 4 times",
          "risk": "low",
          "reason": "Overuse of 'led' can signal inflated ownership",
          "suggested_fix": "Vary with 'built', 'designed', 'managed', or 'co-led' as appropriate"
        }
      ]
    },
    "cover_note": {
      "slop_flags": 1,
      "changed_lines": 0,
      "realism_concerns": 0
    },
    "recruiter_message": {
      "slop_flags": 0,
      "changed_lines": 0,
      "realism_concerns": 0
    }
  },
  "errors": []
}